<DOMSymbolItem xmlns="http://ns.adobe.com/xfl/2008/" xmlns:xsi="http://www.w3.org/2001/XMLSchema-instance" name="Symbol 191" lastModified="1713310677" linkageClassName="ArmorCraftingMenu_fla.DirectoryFrame_Inventory_42" linkageExportForAS="true">
     <timeline>
          <DOMTimeline name="Symbol 191">
               <layers>
                    <DOMLayer name="Labels Layer" color="#37aae5">
                         <frames>
                              <DOMFrame index="0" keyMode="9728">
                                   <elements/>
                              </DOMFrame>
                              <DOMFrame index="1" keyMode="9728" name="rollOn" labelType="name">
                                   <elements/>
                              </DOMFrame>
                              <DOMFrame index="2" duration="44" keyMode="9728">
                                   <elements/>
                              </DOMFrame>
                              <DOMFrame index="46" keyMode="9728" name="rollOff" labelType="name">
                                   <elements/>
                              </DOMFrame>
                         </frames>
                    </DOMLayer>
                    <DOMLayer name="Script Layer" color="#3cc4db">
                         <frames>
                              <DOMFrame index="0" keyMode="9728">
                                   <Actionscript>
                                        <script>stop();
</script>
                                   </Actionscript>
                                   <elements/>
                              </DOMFrame>
                              <DOMFrame index="1" duration="44" keyMode="9728">
                                   <elements/>
                              </DOMFrame>
                              <DOMFrame index="45" keyMode="9728">
                                   <Actionscript>
                                        <script>stop();
</script>
                                   </Actionscript>
                                   <elements/>
                              </DOMFrame>
                              <DOMFrame index="46" duration="29" keyMode="9728">
                                   <elements/>
                              </DOMFrame>
                              <DOMFrame index="75" keyMode="9728">
                                   <Actionscript>
                                        <script>stop();
</script>
                                   </Actionscript>
                                   <elements/>
                              </DOMFrame>
                         </frames>
                    </DOMLayer>
                    <DOMLayer name="Layer 3" color="#bb58a0">
                         <frames>
                              <DOMFrame index="0" duration="28" keyMode="9728">
                                   <elements>
                                        <DOMSymbolInstance libraryItemName="Symbol 190" name="Label_mc" centerPoint3DX="293.5" centerPoint3DY="15.95">
                                             <matrix>
                                                  <Matrix tx="16.95" ty="4.95"/>
                                             </matrix>
                                             <transformationPoint>
                                                  <Point/>
                                             </transformationPoint>
                                             <color>
                                                  <Color alphaMultiplier="0.0"/>
                                             </color>
                                        </DOMSymbolInstance>
                                   </elements>
                              </DOMFrame>
                              <DOMFrame index="28" keyMode="9728">
                                   <elements>
                                        <DOMSymbolInstance libraryItemName="Symbol 190" name="Label_mc" centerPoint3DX="293.5" centerPoint3DY="15.95">
                                             <matrix>
                                                  <Matrix tx="16.95" ty="4.95"/>
                                             </matrix>
                                             <transformationPoint>
                                                  <Point/>
                                             </transformationPoint>
                                             <color>
                                                  <Color/>
                                             </color>
                                        </DOMSymbolInstance>
                                   </elements>
                              </DOMFrame>
                              <DOMFrame index="29" keyMode="9728">
                                   <elements>
                                        <DOMSymbolInstance libraryItemName="Symbol 190" name="Label_mc" centerPoint3DX="293.5" centerPoint3DY="15.95">
                                             <matrix>
                                                  <Matrix tx="16.95" ty="4.95"/>
                                             </matrix>
                                             <transformationPoint>
                                                  <Point/>
                                             </transformationPoint>
                                             <color>
                                                  <Color alphaMultiplier="0.0"/>
                                             </color>
                                        </DOMSymbolInstance>
                                   </elements>
                              </DOMFrame>
                              <DOMFrame index="30" keyMode="9728">
                                   <elements>
                                        <DOMSymbolInstance libraryItemName="Symbol 190" name="Label_mc" centerPoint3DX="293.5" centerPoint3DY="15.95">
                                             <matrix>
                                                  <Matrix tx="16.95" ty="4.95"/>
                                             </matrix>
                                             <transformationPoint>
                                                  <Point/>
                                             </transformationPoint>
                                             <color>
                                                  <Color/>
                                             </color>
                                        </DOMSymbolInstance>
                                   </elements>
                              </DOMFrame>
                              <DOMFrame index="31" keyMode="9728">
                                   <elements>
                                        <DOMSymbolInstance libraryItemName="Symbol 190" name="Label_mc" centerPoint3DX="293.5" centerPoint3DY="15.95">
                                             <matrix>
                                                  <Matrix tx="16.95" ty="4.95"/>
                                             </matrix>
                                             <transformationPoint>
                                                  <Point/>
                                             </transformationPoint>
                                             <color>
                                                  <Color alphaMultiplier="0.0"/>
                                             </color>
                                        </DOMSymbolInstance>
                                   </elements>
                              </DOMFrame>
                              <DOMFrame index="32" duration="20" keyMode="9728">
                                   <elements>
                                        <DOMSymbolInstance libraryItemName="Symbol 190" name="Label_mc" centerPoint3DX="293.5" centerPoint3DY="15.95">
                                             <matrix>
                                                  <Matrix tx="16.95" ty="4.95"/>
                                             </matrix>
                                             <transformationPoint>
                                                  <Point/>
                                             </transformationPoint>
                                             <color>
                                                  <Color/>
                                             </color>
                                        </DOMSymbolInstance>
                                   </elements>
                              </DOMFrame>
                              <DOMFrame index="52" keyMode="9728">
                                   <elements>
                                        <DOMSymbolInstance libraryItemName="Symbol 190" name="Label_mc" centerPoint3DX="293.5" centerPoint3DY="15.95">
                                             <matrix>
                                                  <Matrix tx="16.95" ty="4.95"/>
                                             </matrix>
                                             <transformationPoint>
                                                  <Point/>
                                             </transformationPoint>
                                             <color>
                                                  <Color alphaMultiplier="0.0"/>
                                             </color>
                                        </DOMSymbolInstance>
                                   </elements>
                              </DOMFrame>
                              <DOMFrame index="53" keyMode="9728">
                                   <elements>
                                        <DOMSymbolInstance libraryItemName="Symbol 190" name="Label_mc" centerPoint3DX="293.5" centerPoint3DY="15.95">
                                             <matrix>
                                                  <Matrix tx="16.95" ty="4.95"/>
                                             </matrix>
                                             <transformationPoint>
                                                  <Point/>
                                             </transformationPoint>
                                             <color>
                                                  <Color/>
                                             </color>
                                        </DOMSymbolInstance>
                                   </elements>
                              </DOMFrame>
                              <DOMFrame index="54" duration="22" keyMode="9728">
                                   <elements>
                                        <DOMSymbolInstance libraryItemName="Symbol 190" name="Label_mc" centerPoint3DX="293.5" centerPoint3DY="15.95">
                                             <matrix>
                                                  <Matrix tx="16.95" ty="4.95"/>
                                             </matrix>
                                             <transformationPoint>
                                                  <Point/>
                                             </transformationPoint>
                                             <color>
                                                  <Color alphaMultiplier="0.0"/>
                                             </color>
                                        </DOMSymbolInstance>
                                   </elements>
                              </DOMFrame>
                         </frames>
                    </DOMLayer>
                    <DOMLayer name="Layer 4" color="#f3ecdc">
                         <frames>
                              <DOMFrame index="0" duration="23" keyMode="9728">
                                   <elements>
                                        <DOMSymbolInstance libraryItemName="Symbol 188" centerPoint3DX="490.0" centerPoint3DY="15.0">
                                             <matrix>
                                                  <Matrix tx="0.0" ty="0.0"/>
                                             </matrix>
                                             <transformationPoint>
                                                  <Point/>
                                             </transformationPoint>
                                             <color>
                                                  <Color alphaMultiplier="0.0"/>
                                             </color>
                                        </DOMSymbolInstance>
                                   </elements>
                              </DOMFrame>
                              <DOMFrame index="23" keyMode="9728">
                                   <elements>
                                        <DOMSymbolInstance libraryItemName="Symbol 188" centerPoint3DX="490.0" centerPoint3DY="15.0">
                                             <matrix>
                                                  <Matrix tx="0.0" ty="0.0" a="1.0" d="0.133331298828125"/>
                                             </matrix>
                                             <transformationPoint>
                                                  <Point/>
                                             </transformationPoint>
                                             <color>
                                                  <Color alphaMultiplier="0.0"/>
                                             </color>
                                        </DOMSymbolInstance>
                                   </elements>
                              </DOMFrame>
                              <DOMFrame index="24" keyMode="9728">
                                   <elements>
                                        <DOMSymbolInstance libraryItemName="Symbol 188" centerPoint3DX="490.0" centerPoint3DY="15.0">
                                             <matrix>
                                                  <Matrix tx="0.0" ty="0.0" a="1.0" d="0.3499908447265625"/>
                                             </matrix>
                                             <transformationPoint>
                                                  <Point/>
                                             </transformationPoint>
                                             <color>
                                                  <Color alphaMultiplier="0.25"/>
                                             </color>
                                        </DOMSymbolInstance>
                                   </elements>
                              </DOMFrame>
                              <DOMFrame index="25" keyMode="9728">
                                   <elements>
                                        <DOMSymbolInstance libraryItemName="Symbol 188" centerPoint3DX="490.0" centerPoint3DY="15.05">
                                             <matrix>
                                                  <Matrix tx="0.0" ty="0.05" a="1.0" d="0.566650390625"/>
                                             </matrix>
                                             <transformationPoint>
                                                  <Point/>
                                             </transformationPoint>
                                             <color>
                                                  <Color alphaMultiplier="0.5"/>
                                             </color>
                                        </DOMSymbolInstance>
                                   </elements>
                              </DOMFrame>
                              <DOMFrame index="26" keyMode="9728">
                                   <elements>
                                        <DOMSymbolInstance libraryItemName="Symbol 188" centerPoint3DX="490.0" centerPoint3DY="15.0">
                                             <matrix>
                                                  <Matrix tx="0.0" ty="0.0" a="1.0" d="0.7833251953125"/>
                                             </matrix>
                                             <transformationPoint>
                                                  <Point/>
                                             </transformationPoint>
                                             <color>
                                                  <Color alphaMultiplier="0.75"/>
                                             </color>
                                        </DOMSymbolInstance>
                                   </elements>
                              </DOMFrame>
                              <DOMFrame index="27" duration="31" keyMode="9728">
                                   <elements>
                                        <DOMSymbolInstance libraryItemName="Symbol 188" centerPoint3DX="490.0" centerPoint3DY="15.0">
                                             <matrix>
                                                  <Matrix tx="0.0" ty="0.0"/>
                                             </matrix>
                                             <transformationPoint>
                                                  <Point/>
                                             </transformationPoint>
                                             <color>
                                                  <Color/>
                                             </color>
                                        </DOMSymbolInstance>
                                   </elements>
                              </DOMFrame>
                              <DOMFrame index="58" keyMode="9728">
                                   <elements>
                                        <DOMSymbolInstance libraryItemName="Symbol 188" centerPoint3DX="490.0" centerPoint3DY="15.05">
                                             <matrix>
                                                  <Matrix tx="0.0" ty="0.05" a="1.0" d="0.5666656494140625"/>
                                             </matrix>
                                             <transformationPoint>
                                                  <Point/>
                                             </transformationPoint>
                                             <color>
                                                  <Color/>
                                             </color>
                                        </DOMSymbolInstance>
                                   </elements>
                              </DOMFrame>
                              <DOMFrame index="59" keyMode="9728">
                                   <elements>
                                        <DOMSymbolInstance libraryItemName="Symbol 188" centerPoint3DX="490.0" centerPoint3DY="15.0">
                                             <matrix>
                                                  <Matrix tx="0.0" ty="0.0" a="1.0" d="0.133331298828125"/>
                                             </matrix>
                                             <transformationPoint>
                                                  <Point/>
                                             </transformationPoint>
                                             <color>
                                                  <Color/>
                                             </color>
                                        </DOMSymbolInstance>
                                   </elements>
                              </DOMFrame>
                              <DOMFrame index="60" duration="16" keyMode="9728">
                                   <elements>
                                        <DOMSymbolInstance libraryItemName="Symbol 188" centerPoint3DX="490.0" centerPoint3DY="15.0">
                                             <matrix>
                                                  <Matrix tx="0.0" ty="0.0" a="1.0" d="0.133331298828125"/>
                                             </matrix>
                                             <transformationPoint>
                                                  <Point/>
                                             </transformationPoint>
                                             <color>
                                                  <Color alphaMultiplier="0.0"/>
                                             </color>
                                        </DOMSymbolInstance>
                                   </elements>
                              </DOMFrame>
                         </frames>
                    </DOMLayer>
                    <DOMLayer name="Layer 5" color="#dc0fcc" current="true" isSelected="true">
                         <frames>
                              <DOMFrame index="0" duration="8" keyMode="9728">
                                   <elements>
                                        <DOMSymbolInstance libraryItemName="Symbol 187" centerPoint3DX="490.0" centerPoint3DY="213.95">
                                             <matrix>
                                                  <Matrix tx="0.0" ty="0.45"/>
                                             </matrix>
                                             <transformationPoint>
                                                  <Point/>
                                             </transformationPoint>
                                             <color>
                                                  <Color alphaMultiplier="0.0"/>
                                             </color>
                                        </DOMSymbolInstance>
                                   </elements>
                              </DOMFrame>
                              <DOMFrame index="8" keyMode="9728">
                                   <elements>
                                        <DOMSymbolInstance libraryItemName="Symbol 187" centerPoint3DX="490.0" centerPoint3DY="213.95">
                                             <matrix>
                                                  <Matrix tx="0.0" ty="0.45" a="0.110198974609375" d="0.1314544677734375"/>
                                             </matrix>
                                             <transformationPoint>
                                                  <Point/>
                                             </transformationPoint>
                                             <color>
                                                  <Color alphaMultiplier="0.0"/>
                                             </color>
                                        </DOMSymbolInstance>
                                   </elements>
                              </DOMFrame>
                              <DOMFrame index="9" keyMode="9728">
                                   <elements>
                                        <DOMSymbolInstance libraryItemName="Symbol 187" centerPoint3DX="490.0" centerPoint3DY="213.95">
                                             <matrix>
                                                  <Matrix tx="0.0" ty="0.45" a="0.1695098876953125" d="0.1893463134765625"/>
                                             </matrix>
                                             <transformationPoint>
                                                  <Point/>
                                             </transformationPoint>
                                             <color>
                                                  <Color alphaMultiplier="0.06640625"/>
                                             </color>
                                        </DOMSymbolInstance>
                                   </elements>
                              </DOMFrame>
                              <DOMFrame index="10" keyMode="9728">
                                   <elements>
                                        <DOMSymbolInstance libraryItemName="Symbol 187" centerPoint3DX="490.05" centerPoint3DY="213.9">
                                             <matrix>
                                                  <Matrix tx="0.05" ty="0.4" a="0.22882080078125" d="0.2472381591796875"/>
                                             </matrix>
                                             <transformationPoint>
                                                  <Point/>
                                             </transformationPoint>
                                             <color>
                                                  <Color alphaMultiplier="0.1328125"/>
                                             </color>
                                        </DOMSymbolInstance>
                                   </elements>
                              </DOMFrame>
                              <DOMFrame index="11" keyMode="9728">
                                   <elements>
                                        <DOMSymbolInstance libraryItemName="Symbol 187" centerPoint3DX="490.05" centerPoint3DY="213.95">
                                             <matrix>
                                                  <Matrix tx="0.05" ty="0.45" a="0.28814697265625" d="0.305145263671875"/>
                                             </matrix>
                                             <transformationPoint>
                                                  <Point/>
                                             </transformationPoint>
                                             <color>
                                                  <Color alphaMultiplier="0.19921875"/>
                                             </color>
                                        </DOMSymbolInstance>
                                   </elements>
                              </DOMFrame>
                              <DOMFrame index="12" keyMode="9728">
                                   <elements>
                                        <DOMSymbolInstance libraryItemName="Symbol 187" centerPoint3DX="490.0" centerPoint3DY="213.95">
                                             <matrix>
                                                  <Matrix tx="0.0" ty="0.45" a="0.3474578857421875" d="0.3630523681640625"/>
                                             </matrix>
                                             <transformationPoint>
                                                  <Point/>
                                             </transformationPoint>
                                             <color>
                                                  <Color alphaMultiplier="0.265625"/>
                                             </color>
                                        </DOMSymbolInstance>
                                   </elements>
                              </DOMFrame>
                              <DOMFrame index="13" keyMode="9728">
                                   <elements>
                                        <DOMSymbolInstance libraryItemName="Symbol 187" centerPoint3DX="490.05" centerPoint3DY="213.95">
                                             <matrix>
                                                  <Matrix tx="0.05" ty="0.45" a="0.4067840576171875" d="0.4209442138671875"/>
                                             </matrix>
                                             <transformationPoint>
                                                  <Point/>
                                             </transformationPoint>
                                             <color>
                                                  <Color alphaMultiplier="0.33203125"/>
                                             </color>
                                        </DOMSymbolInstance>
                                   </elements>
                              </DOMFrame>
                              <DOMFrame index="14" keyMode="9728">
                                   <elements>
                                        <DOMSymbolInstance libraryItemName="Symbol 187" centerPoint3DX="490.05" centerPoint3DY="213.95">
                                             <matrix>
                                                  <Matrix tx="0.05" ty="0.45" a="0.466094970703125" d="0.478851318359375"/>
                                             </matrix>
                                             <transformationPoint>
                                                  <Point/>
                                             </transformationPoint>
                                             <color>
                                                  <Color alphaMultiplier="0.3984375"/>
                                             </color>
                                        </DOMSymbolInstance>
                                   </elements>
                              </DOMFrame>
                              <DOMFrame index="15" keyMode="9728">
                                   <elements>
                                        <DOMSymbolInstance libraryItemName="Symbol 187" centerPoint3DX="490.0" centerPoint3DY="213.95">
                                             <matrix>
                                                  <Matrix tx="0.0" ty="0.45" a="0.525421142578125" d="0.5367584228515625"/>
                                             </matrix>
                                             <transformationPoint>
                                                  <Point/>
                                             </transformationPoint>
                                             <color>
                                                  <Color alphaMultiplier="0.46484375"/>
                                             </color>
                                        </DOMSymbolInstance>
                                   </elements>
                              </DOMFrame>
                              <DOMFrame index="16" keyMode="9728">
                                   <elements>
                                        <DOMSymbolInstance libraryItemName="Symbol 187" centerPoint3DX="490.05" centerPoint3DY="213.95">
                                             <matrix>
                                                  <Matrix tx="0.05" ty="0.45" a="0.584747314453125" d="0.59466552734375"/>
                                             </matrix>
                                             <transformationPoint>
                                                  <Point/>
                                             </transformationPoint>
                                             <color>
                                                  <Color alphaMultiplier="0.53515625"/>
                                             </color>
                                        </DOMSymbolInstance>
                                   </elements>
                              </DOMFrame>
                              <DOMFrame index="17" keyMode="9728">
                                   <elements>
                                        <DOMSymbolInstance libraryItemName="Symbol 187" centerPoint3DX="490.0" centerPoint3DY="213.95">
                                             <matrix>
                                                  <Matrix tx="0.0" ty="0.45" a="0.644073486328125" d="0.6525726318359375"/>
                                             </matrix>
                                             <transformationPoint>
                                                  <Point/>
                                             </transformationPoint>
                                             <color>
                                                  <Color alphaMultiplier="0.6015625"/>
                                             </color>
                                        </DOMSymbolInstance>
                                   </elements>
                              </DOMFrame>
                              <DOMFrame index="18" keyMode="9728">
                                   <elements>
                                        <DOMSymbolInstance libraryItemName="Symbol 187" centerPoint3DX="490.0" centerPoint3DY="213.95">
                                             <matrix>
                                                  <Matrix tx="0.0" ty="0.45" a="0.7033843994140625" d="0.710479736328125"/>
                                             </matrix>
                                             <transformationPoint>
                                                  <Point/>
                                             </transformationPoint>
                                             <color>
                                                  <Color alphaMultiplier="0.66796875"/>
                                             </color>
                                        </DOMSymbolInstance>
                                   </elements>
                              </DOMFrame>
                              <DOMFrame index="19" keyMode="9728">
                                   <elements>
                                        <DOMSymbolInstance libraryItemName="Symbol 187" centerPoint3DX="490.05" centerPoint3DY="213.95">
                                             <matrix>
                                                  <Matrix tx="0.05" ty="0.45" a="0.7627105712890625" d="0.76837158203125"/>
                                             </matrix>
                                             <transformationPoint>
                                                  <Point/>
                                             </transformationPoint>
                                             <color>
                                                  <Color alphaMultiplier="0.734375"/>
                                             </color>
                                        </DOMSymbolInstance>
                                   </elements>
                              </DOMFrame>
                              <DOMFrame index="20" keyMode="9728">
                                   <elements>
                                        <DOMSymbolInstance libraryItemName="Symbol 187" centerPoint3DX="490.05" centerPoint3DY="213.95">
                                             <matrix>
                                                  <Matrix tx="0.05" ty="0.45" a="0.822021484375" d="0.8262786865234375"/>
                                             </matrix>
                                             <transformationPoint>
                                                  <Point/>
                                             </transformationPoint>
                                             <color>
                                                  <Color alphaMultiplier="0.80078125"/>
                                             </color>
                                        </DOMSymbolInstance>
                                   </elements>
                              </DOMFrame>
                              <DOMFrame index="21" keyMode="9728">
                                   <elements>
                                        <DOMSymbolInstance libraryItemName="Symbol 187" centerPoint3DX="490.0" centerPoint3DY="214.0">
                                             <matrix>
                                                  <Matrix tx="0.0" ty="0.5" a="0.88134765625" d="0.884185791015625"/>
                                             </matrix>
                                             <transformationPoint>
                                                  <Point/>
                                             </transformationPoint>
                                             <color>
                                                  <Color alphaMultiplier="0.8671875"/>
                                             </color>
                                        </DOMSymbolInstance>
                                   </elements>
                              </DOMFrame>
                              <DOMFrame index="22" keyMode="9728">
                                   <elements>
                                        <DOMSymbolInstance libraryItemName="Symbol 187" centerPoint3DX="490.05" centerPoint3DY="213.95">
                                             <matrix>
                                                  <Matrix tx="0.05" ty="0.45" a="0.9406585693359375" d="0.94207763671875"/>
                                             </matrix>
                                             <transformationPoint>
                                                  <Point/>
                                             </transformationPoint>
                                             <color>
                                                  <Color alphaMultiplier="0.93359375"/>
                                             </color>
                                        </DOMSymbolInstance>
                                   </elements>
                              </DOMFrame>
                              <DOMFrame index="23" keyMode="9728">
                                   <elements>
                                        <DOMSymbolInstance libraryItemName="Symbol 187" centerPoint3DX="490.0" centerPoint3DY="213.95">
                                             <matrix>
                                                  <Matrix tx="0.0" ty="0.45"/>
                                             </matrix>
                                             <transformationPoint>
                                                  <Point/>
                                             </transformationPoint>
                                             <color>
                                                  <Color/>
                                             </color>
                                        </DOMSymbolInstance>
                                   </elements>
                              </DOMFrame>
                              <DOMFrame index="24" keyMode="9728">
                                   <elements>
                                        <DOMSymbolInstance libraryItemName="Symbol 187" centerPoint3DX="490.0" centerPoint3DY="213.95">
                                             <matrix>
                                                  <Matrix tx="0.0" ty="0.45"/>
                                             </matrix>
                                             <transformationPoint>
                                                  <Point/>
                                             </transformationPoint>
                                             <color>
                                                  <Color alphaMultiplier="0.0"/>
                                             </color>
                                        </DOMSymbolInstance>
                                   </elements>
                              </DOMFrame>
                              <DOMFrame index="25" keyMode="9728">
                                   <elements>
                                        <DOMSymbolInstance libraryItemName="Symbol 187" centerPoint3DX="490.0" centerPoint3DY="213.95">
                                             <matrix>
                                                  <Matrix tx="0.0" ty="0.45"/>
                                             </matrix>
                                             <transformationPoint>
                                                  <Point/>
                                             </transformationPoint>
                                             <color>
                                                  <Color/>
                                             </color>
                                        </DOMSymbolInstance>
                                   </elements>
                              </DOMFrame>
                              <DOMFrame index="26" keyMode="9728">
                                   <elements>
                                        <DOMSymbolInstance libraryItemName="Symbol 187" centerPoint3DX="490.0" centerPoint3DY="213.95">
                                             <matrix>
                                                  <Matrix tx="0.0" ty="0.45"/>
                                             </matrix>
                                             <transformationPoint>
                                                  <Point/>
                                             </transformationPoint>
                                             <color>
                                                  <Color alphaMultiplier="0.0"/>
                                             </color>
                                        </DOMSymbolInstance>
                                   </elements>
                              </DOMFrame>
                              <DOMFrame index="27" duration="34" keyMode="9728">
                                   <elements>
                                        <DOMSymbolInstance libraryItemName="Symbol 187" centerPoint3DX="490.0" centerPoint3DY="213.95">
                                             <matrix>
                                                  <Matrix tx="0.0" ty="0.45"/>
                                             </matrix>
                                             <transformationPoint>
                                                  <Point/>
                                             </transformationPoint>
                                             <color>
                                                  <Color/>
                                             </color>
                                        </DOMSymbolInstance>
                                   </elements>
                              </DOMFrame>
                              <DOMFrame index="61" keyMode="9728">
                                   <elements>
                                        <DOMSymbolInstance libraryItemName="Symbol 187" centerPoint3DX="490.05" centerPoint3DY="213.95">
                                             <matrix>
                                                  <Matrix tx="0.05" ty="0.45" a="0.9110107421875" d="0.91314697265625"/>
                                             </matrix>
                                             <transformationPoint>
                                                  <Point/>
                                             </transformationPoint>
                                             <color>
                                                  <Color alphaMultiplier="0.8984375"/>
                                             </color>
                                        </DOMSymbolInstance>
                                   </elements>
                              </DOMFrame>
                              <DOMFrame index="62" keyMode="9728">
                                   <elements>
                                        <DOMSymbolInstance libraryItemName="Symbol 187" centerPoint3DX="490.05" centerPoint3DY="213.95">
                                             <matrix>
                                                  <Matrix tx="0.05" ty="0.45" a="0.8220367431640625" d="0.8262939453125"/>
                                             </matrix>
                                             <transformationPoint>
                                                  <Point/>
                                             </transformationPoint>
                                             <color>
                                                  <Color alphaMultiplier="0.80078125"/>
                                             </color>
                                        </DOMSymbolInstance>
                                   </elements>
                              </DOMFrame>
                              <DOMFrame index="63" keyMode="9728">
                                   <elements>
                                        <DOMSymbolInstance libraryItemName="Symbol 187" centerPoint3DX="490.0" centerPoint3DY="213.95">
                                             <matrix>
                                                  <Matrix tx="0.0" ty="0.45" a="0.733062744140625" d="0.73944091796875"/>
                                             </matrix>
                                             <transformationPoint>
                                                  <Point/>
                                             </transformationPoint>
                                             <color>
                                                  <Color alphaMultiplier="0.69921875"/>
                                             </color>
                                        </DOMSymbolInstance>
                                   </elements>
                              </DOMFrame>
                              <DOMFrame index="64" keyMode="9728">
                                   <elements>
                                        <DOMSymbolInstance libraryItemName="Symbol 187" centerPoint3DX="490.0" centerPoint3DY="213.95">
                                             <matrix>
                                                  <Matrix tx="0.0" ty="0.45" a="0.6440887451171875" d="0.652587890625"/>
                                             </matrix>
                                             <transformationPoint>
                                                  <Point/>
                                             </transformationPoint>
                                             <color>
                                                  <Color alphaMultiplier="0.6015625"/>
                                             </color>
                                        </DOMSymbolInstance>
                                   </elements>
                              </DOMFrame>
                              <DOMFrame index="65" keyMode="9728">
                                   <elements>
                                        <DOMSymbolInstance libraryItemName="Symbol 187" centerPoint3DX="490.05" centerPoint3DY="213.95">
                                             <matrix>
                                                  <Matrix tx="0.05" ty="0.45" a="0.5550994873046875" d="0.56573486328125"/>
                                             </matrix>
                                             <transformationPoint>
                                                  <Point/>
                                             </transformationPoint>
                                             <color>
                                                  <Color alphaMultiplier="0.5"/>
                                             </color>
                                        </DOMSymbolInstance>
                                   </elements>
                              </DOMFrame>
                              <DOMFrame index="66" keyMode="9728">
                                   <elements>
                                        <DOMSymbolInstance libraryItemName="Symbol 187" centerPoint3DX="490.05" centerPoint3DY="213.95">
                                             <matrix>
                                                  <Matrix tx="0.05" ty="0.45" a="0.4661102294921875" d="0.4788665771484375"/>
                                             </matrix>
                                             <transformationPoint>
                                                  <Point/>
                                             </transformationPoint>
                                             <color>
                                                  <Color alphaMultiplier="0.3984375"/>
                                             </color>
                                        </DOMSymbolInstance>
                                   </elements>
                              </DOMFrame>
                              <DOMFrame index="67" keyMode="9728">
                                   <elements>
                                        <DOMSymbolInstance libraryItemName="Symbol 187" centerPoint3DX="490.05" centerPoint3DY="213.95">
                                             <matrix>
                                                  <Matrix tx="0.05" ty="0.45" a="0.37713623046875" d="0.3920135498046875"/>
                                             </matrix>
                                             <transformationPoint>
                                                  <Point/>
                                             </transformationPoint>
                                             <color>
                                                  <Color alphaMultiplier="0.30078125"/>
                                             </color>
                                        </DOMSymbolInstance>
                                   </elements>
                              </DOMFrame>
                              <DOMFrame index="68" keyMode="9728">
                                   <elements>
                                        <DOMSymbolInstance libraryItemName="Symbol 187" centerPoint3DX="490.05" centerPoint3DY="213.95">
                                             <matrix>
                                                  <Matrix tx="0.05" ty="0.45" a="0.2881622314453125" d="0.3051605224609375"/>
                                             </matrix>
                                             <transformationPoint>
                                                  <Point/>
                                             </transformationPoint>
                                             <color>
                                                  <Color alphaMultiplier="0.19921875"/>
                                             </color>
                                        </DOMSymbolInstance>
                                   </elements>
                              </DOMFrame>
                              <DOMFrame index="69" keyMode="9728">
                                   <elements>
                                        <DOMSymbolInstance libraryItemName="Symbol 187" centerPoint3DX="490.0" centerPoint3DY="213.95">
                                             <matrix>
                                                  <Matrix tx="0.0" ty="0.45" a="0.199188232421875" d="0.2183074951171875"/>
                                             </matrix>
                                             <transformationPoint>
                                                  <Point/>
                                             </transformationPoint>
                                             <color>
                                                  <Color alphaMultiplier="0.1015625"/>
                                             </color>
                                        </DOMSymbolInstance>
                                   </elements>
                              </DOMFrame>
                              <DOMFrame index="70" duration="6" keyMode="9728">
                                   <elements>
                                        <DOMSymbolInstance libraryItemName="Symbol 187" centerPoint3DX="490.0" centerPoint3DY="213.95">
                                             <matrix>
                                                  <Matrix tx="0.0" ty="0.45" a="0.110198974609375" d="0.1314544677734375"/>
                                             </matrix>
                                             <transformationPoint>
                                                  <Point/>
                                             </transformationPoint>
                                             <color>
                                                  <Color alphaMultiplier="0.0"/>
                                             </color>
                                        </DOMSymbolInstance>
                                   </elements>
                              </DOMFrame>
                         </frames>
                    </DOMLayer>
               </layers>
          </DOMTimeline>
     </timeline>
</DOMSymbolItem>
