<DOMDocument xmlns="http://ns.adobe.com/xfl/2008/" xmlns:xsi="http://www.w3.org/2001/XMLSchema-instance" currentTimeline="1" xflVersion="2.2" creatorInfo="JPEXS Free Flash Decompiler" platform="Windows" versionInfo="Saved by JPEXS Free Flash Decompiler v.20.1.0" majorVersion="20.1.0" buildNumber="" nextSceneIdentifier="2" playOptionsPlayLoop="false" playOptionsPlayPages="false" playOptionsPlayFrameActions="false" autoSaveHasPrompted="true" backgroundColor="#acacac" frameRate="30" width="1920" height="1080">
     <fonts>
          <DOMFontItem name="Font 77" font="Consolas" size="0" id="77" embedRanges="1|2|3|4|5" embeddedCharacters="ˆ˜–—‘’‚“”„†‡•…‰‹›€™"/>
          <DOMFontItem name="Font 78" font="Genesis Controller  Buttons" size="0" id="78" embedRanges="1|2|3" embeddedCharacters="+/"/>
          <DOMFontItem name="Font 79" font="NB Architekt Light" size="0" id="79" embedRanges="1|2|3|4|5" embeddedCharacters="&#10;&#13;¡¢£¤¥¦§¨©ª«¬­®¯°±²³´µ¶·¸¹º»¼½¾¿ÀÁÂÃÄÅÆÇÈÉÊËÌÍÎÏÐÑÒÓÔÕÖ×ØÙÚÛÜÝÞßàáâãäåæçèéêëìíîïðñòóôõö÷øùúûüýþÿĀāĂăĄąĆćĈĉĐĘęıŁłŃńŒœŚśŠšŸŹźŻżŽžƒˆˇˉ˘˙˚˛˜˝Δμπ‐‑‒–—‘’‚“”„†‡•…‰‹›⁄€™Ω←↑→↓∂∏∑∕√∞∫≠≤≥"/>
          <DOMFontItem name="Font 80" font="NB Grotesk R Semibold" size="0" id="80" embedRanges="1|2|3|4|5" embeddedCharacters=" &#10;&#13;¡¢£¤¥¦§¨©ª«¬­®¯°±²³´µ¶·¸¹º»¼½¾¿ÀÁÂÃÄÅÆÇÈÉÊËÌÍÎÏÐÑÒÓÔÕÖ×ØÙÚÛÜÝÞßàáâãäåæçèéêëìíîïðñòóôõö÷øùúûüýþÿĀāĂăĄąĆćĈĉĐĘęğıŁłŃńŒœřŚśŠšŸŹźŻżŽžƒˆˇˉ˘˙˚˛˜˝Δμπ–—‘’‚“”„†‡•…‰′‹›⁄€™Ω∂∏∑∕√∞∫≠≤≥"/>
          <DOMFontItem name="Font 81" font="NB Grotesk R Bold" size="0" id="81" embedRanges="1|2|3|4|5" embeddedCharacters=" &#10;&#13;¡¢£¤¥¦§¨©ª«¬­®¯°±²³´µ¶·¸¹º»¼½¾¿ÀÁÂÃÄÅÆÇÈÉÊËÌÍÎÏÐÑÒÓÔÕÖ×ØÙÚÛÜÝÞßàáâãäåæçèéêëìíîïðñòóôõö÷øùúûüýþÿĀāĂăĄąĆćĈĉĐĘęğıŁłŃńŒœřŚśŠšŸŹźŻżŽžƒˆˇˉ˘˙˚˛˜˝Δμπ–—‘’‚“”„†‡•…‰‹›⁄€™Ω∂∏∑∕√∞∫≠≤≥"/>
          <DOMFontItem name="Font 82" font="Genesis Controller Buttons thin" size="0" id="82" embedRanges="1|2|3" embeddedCharacters="&#13;+/"/>
          <DOMFontItem name="Font 83" font="NB Architekt" size="0" id="83" embedRanges="1|2|3|4|5" embeddedCharacters="&#10;&#13;¡¢£¤¥¦§¨©ª«¬­®¯°±²³´µ¶·¸¹º»¼½¾¿ÀÁÂÃÄÅÆÇÈÉÊËÌÍÎÏÐÑÒÓÔÕÖ×ØÙÚÛÜÝÞßàáâãäåæçèéêëìíîïðñòóôõö÷øùúûüýþÿĀāĂăĄąĆćĈĉĐĘęıŁłŃńŒœŚśŠšŸŹźŻżŽžƒˆˇˉ˘˙˚˛˜˝Δμπ‐‑‒–—―‘’‚“”„†‡•…‰‹›⁄€™Ω←↑→↓∂∏∑∕√∞∫≠≤≥﹘﹣－"/>
          <DOMFontItem name="Font 84" font="Genesis Controller  Buttons inv" size="0" id="84" embedRanges="1|2|3" embeddedCharacters="&#13;+/"/>
          <DOMFontItem name="Font 85" font="ArialMT" size="0" id="85" embedRanges="1|2|3|4|5" embeddedCharacters="ˆ˜–—‘’‚“”„†‡•…‰‹›€™"/>
          <DOMFontItem name="Font 86" font="Handwritten_Institute" size="0" id="86" embedRanges="1|2|3" embeddedCharacters="!&quot;#$%&amp;'()*+,-./:;&lt;=&gt;?@[\]^_{|}~¡¢£¤§©«¬®°±²µ¶»¿ÀÁÂÃÄÅÆÇÈÉÊËÌÍÎÏÐÑÒÓÔÕÖØÙÚÛÜÝÞßàáâãäåæçèéêëìíîïðñòóôõöøùúûüýþÿĄąĆćĈĉĔęĜĝĤĥıĴĵŁłŃńŐőŒœŚśŜŝŠšŬŭŰűŸŹźŻżŽžƒμ‘’“”†‡•€™"/>
     </fonts>
     <symbols>
          <Include href="Symbol 2.xml" loadImmediate="false" lastModified="1713310678"/>
          <Include href="Symbol 3.xml" loadImmediate="false" lastModified="1713310678"/>
          <Include href="Symbol 5.xml" loadImmediate="false" lastModified="1713310678"/>
          <Include href="Symbol 7.xml" loadImmediate="false" lastModified="1713310678"/>
          <Include href="Symbol 9.xml" loadImmediate="false" lastModified="1713310678"/>
          <Include href="Symbol 11.xml" loadImmediate="false" lastModified="1713310678"/>
          <Include href="Symbol 13.xml" loadImmediate="false" lastModified="1713310678"/>
          <Include href="Symbol 15.xml" loadImmediate="false" lastModified="1713310678"/>
          <Include href="Symbol 16.xml" itemIcon="1" loadImmediate="false" lastModified="1713310678"/>
          <Include href="Symbol 18.xml" loadImmediate="false" lastModified="1713310678"/>
          <Include href="Symbol 19.xml" loadImmediate="false" lastModified="1713310678"/>
          <Include href="Symbol 21.xml" loadImmediate="false" lastModified="1713310678"/>
          <Include href="Symbol 23.xml" loadImmediate="false" lastModified="1713310678"/>
          <Include href="Symbol 25.xml" loadImmediate="false" lastModified="1713310678"/>
          <Include href="Symbol 26.xml" itemIcon="1" loadImmediate="false" lastModified="1713310678"/>
          <Include href="Symbol 28.xml" itemIcon="1" loadImmediate="false" lastModified="1713310678"/>
          <Include href="Symbol 29.xml" loadImmediate="false" lastModified="1713310678"/>
          <Include href="Symbol 30.xml" loadImmediate="false" lastModified="1713310678"/>
          <Include href="Symbol 32.xml" loadImmediate="false" lastModified="1713310678"/>
          <Include href="Symbol 33.xml" itemIcon="1" loadImmediate="false" lastModified="1713310678"/>
          <Include href="Symbol 34.xml" itemIcon="1" loadImmediate="false" lastModified="1713310678"/>
          <Include href="Symbol 35.xml" itemIcon="1" loadImmediate="false" lastModified="1713310678"/>
          <Include href="Symbol 36.xml" itemIcon="1" loadImmediate="false" lastModified="1713310678"/>
          <Include href="Symbol 37.xml" itemIcon="1" loadImmediate="false" lastModified="1713310678"/>
          <Include href="Symbol 38.xml" itemIcon="1" loadImmediate="false" lastModified="1713310678"/>
          <Include href="Symbol 39.xml" loadImmediate="false" lastModified="1713310678"/>
          <Include href="Symbol 40.xml" loadImmediate="false" lastModified="1713310678"/>
          <Include href="Symbol 41.xml" loadImmediate="false" lastModified="1713310678"/>
          <Include href="Symbol 42.xml" itemIcon="1" loadImmediate="false" lastModified="1713310678"/>
          <Include href="Symbol 43.xml" itemIcon="1" loadImmediate="false" lastModified="1713310678"/>
          <Include href="Symbol 45.xml" itemIcon="1" loadImmediate="false" lastModified="1713310678"/>
          <Include href="Symbol 46.xml" loadImmediate="false" lastModified="1713310678"/>
          <Include href="Symbol 48.xml" loadImmediate="false" lastModified="1713310678"/>
          <Include href="Symbol 50.xml" loadImmediate="false" lastModified="1713310678"/>
          <Include href="Symbol 52.xml" loadImmediate="false" lastModified="1713310678"/>
          <Include href="Symbol 53.xml" itemIcon="1" loadImmediate="false" lastModified="1713310678"/>
          <Include href="Symbol 54.xml" loadImmediate="false" lastModified="1713310678"/>
          <Include href="Symbol 55.xml" loadImmediate="false" lastModified="1713310678"/>
          <Include href="Symbol 56.xml" loadImmediate="false" lastModified="1713310678"/>
          <Include href="Symbol 58.xml" loadImmediate="false" lastModified="1713310678"/>
          <Include href="Symbol 63.xml" loadImmediate="false" lastModified="1713310678"/>
          <Include href="Symbol 64.xml" itemIcon="1" loadImmediate="false" lastModified="1713310678"/>
          <Include href="Symbol 65.xml" itemIcon="1" loadImmediate="false" lastModified="1713310678"/>
          <Include href="Symbol 66.xml" itemIcon="1" loadImmediate="false" lastModified="1713310678"/>
          <Include href="Symbol 67.xml" loadImmediate="false" lastModified="1713310678"/>
          <Include href="Symbol 68.xml" loadImmediate="false" lastModified="1713310678"/>
          <Include href="Symbol 74.xml" loadImmediate="false" lastModified="1713310678"/>
          <Include href="Symbol 75.xml" loadImmediate="false" lastModified="1713310678"/>
          <Include href="Symbol 76.xml" loadImmediate="false" lastModified="1713310678"/>
     </symbols>
     <timelines>
          <DOMTimeline name="Scene 1">
               <layers>
                    <DOMLayer name="Layer 1" color="#5884a4" current="true" isSelected="true">
                         <frames>
                              <DOMFrame index="0" keyMode="9728">
                                   <elements>
                                        <DOMSymbolInstance libraryItemName="Symbol 76" name="Menu_mc" centerPoint3DX="1685.15" centerPoint3DY="535.5">
                                             <matrix>
                                                  <Matrix tx="1495.0" ty="160.0"/>
                                             </matrix>
                                             <transformationPoint>
                                                  <Point/>
                                             </transformationPoint>
                                        </DOMSymbolInstance>
                                   </elements>
                              </DOMFrame>
                         </frames>
                    </DOMLayer>
               </layers>
          </DOMTimeline>
     </timelines>
</DOMDocument>
